<annotation>
	<folder></folder>
	<filename>Image_56_jpg.rf.9c8a98323b3b5dcec72b7c9009609edb.jpg</filename>
	<path>Image_56_jpg.rf.9c8a98323b3b5dcec72b7c9009609edb.jpg</path>
	<source>
		<database>roboflow.com</database>
	</source>
	<size>
		<width>320</width>
		<height>320</height>
		<depth>3</depth>
	</size>
	<segmented>0</segmented>
	<object>
		<name>Tempe</name>
		<pose>Unspecified</pose>
		<truncated>0</truncated>
		<difficult>0</difficult>
		<occluded>0</occluded>
		<bndbox>
			<xmin>43</xmin>
			<xmax>279</xmax>
			<ymin>66</ymin>
			<ymax>254</ymax>
		</bndbox>
	</object>
</annotation>
