<annotation>
	<folder></folder>
	<filename>IMG-20211216-WA0060_jpg.rf.64436ff8f96d7fd27ab8e6a97c64bda3.jpg</filename>
	<path>IMG-20211216-WA0060_jpg.rf.64436ff8f96d7fd27ab8e6a97c64bda3.jpg</path>
	<source>
		<database>roboflow.com</database>
	</source>
	<size>
		<width>320</width>
		<height>320</height>
		<depth>3</depth>
	</size>
	<segmented>0</segmented>
	<object>
		<name>Cabai Merah</name>
		<pose>Unspecified</pose>
		<truncated>0</truncated>
		<difficult>0</difficult>
		<occluded>0</occluded>
		<bndbox>
			<xmin>50</xmin>
			<xmax>298</xmax>
			<ymin>11</ymin>
			<ymax>321</ymax>
		</bndbox>
	</object>
</annotation>
