<annotation>
	<folder></folder>
	<filename>IMG20230930154741_jpg.rf.aa67cf6cdb843178e6469dffb3a83059.jpg</filename>
	<path>IMG20230930154741_jpg.rf.aa67cf6cdb843178e6469dffb3a83059.jpg</path>
	<source>
		<database>roboflow.com</database>
	</source>
	<size>
		<width>320</width>
		<height>320</height>
		<depth>3</depth>
	</size>
	<segmented>0</segmented>
	<object>
		<name>Ikan</name>
		<pose>Unspecified</pose>
		<truncated>0</truncated>
		<difficult>0</difficult>
		<occluded>0</occluded>
		<bndbox>
			<xmin>69</xmin>
			<xmax>263</xmax>
			<ymin>139</ymin>
			<ymax>221</ymax>
		</bndbox>
	</object>
</annotation>
