<annotation>
	<folder></folder>
	<filename>IMG20231028150343_jpg.rf.bff6b2f51df3c07e6d90bf80c4857673.jpg</filename>
	<path>IMG20231028150343_jpg.rf.bff6b2f51df3c07e6d90bf80c4857673.jpg</path>
	<source>
		<database>roboflow.com</database>
	</source>
	<size>
		<width>320</width>
		<height>320</height>
		<depth>3</depth>
	</size>
	<segmented>0</segmented>
	<object>
		<name>Ikan</name>
		<pose>Unspecified</pose>
		<truncated>0</truncated>
		<difficult>0</difficult>
		<occluded>0</occluded>
		<bndbox>
			<xmin>69</xmin>
			<xmax>280</xmax>
			<ymin>34</ymin>
			<ymax>297</ymax>
		</bndbox>
	</object>
</annotation>
