<annotation>
	<folder></folder>
	<filename>img_f9e207db-ec66-4d3e-bbb3-c44024b533911634721473392_jpg.rf.60347a8bf9c50d0725aab492326e0334.jpg</filename>
	<path>img_f9e207db-ec66-4d3e-bbb3-c44024b533911634721473392_jpg.rf.60347a8bf9c50d0725aab492326e0334.jpg</path>
	<source>
		<database>roboflow.com</database>
	</source>
	<size>
		<width>320</width>
		<height>320</height>
		<depth>3</depth>
	</size>
	<segmented>0</segmented>
	<object>
		<name>Nasi</name>
		<pose>Unspecified</pose>
		<truncated>0</truncated>
		<difficult>0</difficult>
		<occluded>0</occluded>
		<bndbox>
			<xmin>3</xmin>
			<xmax>141</xmax>
			<ymin>138</ymin>
			<ymax>321</ymax>
		</bndbox>
	</object>
</annotation>
