<annotation>
	<folder></folder>
	<filename>istockphoto-1341645630-612x612_jpg.rf.825aa303223efc4dddc96983b6ba5977.jpg</filename>
	<path>istockphoto-1341645630-612x612_jpg.rf.825aa303223efc4dddc96983b6ba5977.jpg</path>
	<source>
		<database>roboflow.com</database>
	</source>
	<size>
		<width>320</width>
		<height>320</height>
		<depth>3</depth>
	</size>
	<segmented>0</segmented>
	<object>
		<name>Tahu</name>
		<pose>Unspecified</pose>
		<truncated>0</truncated>
		<difficult>0</difficult>
		<occluded>0</occluded>
		<bndbox>
			<xmin>100</xmin>
			<xmax>274</xmax>
			<ymin>7</ymin>
			<ymax>236</ymax>
		</bndbox>
		<polygon>
			<x1>273.189892</x1>
			<y1>175.117224</y1>
			<x2>248.471384</x2>
			<y2>25.780782</y2>
			<x3>111.992514</x3>
			<y3>6.29156</y3>
			<x4>99.228081</x4>
			<y4>59.492268</y4>
			<x5>113.036745</x5>
			<y5>197.542535</y5>
			<x6>245.578805</x6>
			<y6>234.920657</y6>
			<x7>273.189892</x7>
			<y7>175.117224</y7>
		</polygon>
	</object>
	<object>
		<name>Tahu</name>
		<pose>Unspecified</pose>
		<truncated>0</truncated>
		<difficult>0</difficult>
		<occluded>0</occluded>
		<bndbox>
			<xmin>27</xmin>
			<xmax>142</xmax>
			<ymin>94</ymin>
			<ymax>233</ymax>
		</bndbox>
		<polygon>
			<x1>98.188068</x1>
			<y1>92.781285</y1>
			<x2>36.519176</x2>
			<y2>123.294953</y2>
			<x3>26.248235</x3>
			<y3>172.872921</y3>
			<x4>97.313077</x4>
			<y4>231.919563</y4>
			<x5>141.24364</x5>
			<y5>202.692813</y5>
			<x6>98.188068</x6>
			<y6>92.781285</y6>
		</polygon>
	</object>
	<object>
		<name>Tahu</name>
		<pose>Unspecified</pose>
		<truncated>0</truncated>
		<difficult>0</difficult>
		<occluded>0</occluded>
		<bndbox>
			<xmin>55</xmin>
			<xmax>227</xmax>
			<ymin>206</ymin>
			<ymax>314</ymax>
		</bndbox>
		<polygon>
			<x1>74.424134</x1>
			<y1>205.289446</y1>
			<x2>57.707502</x2>
			<y2>233.839418</y2>
			<x3>53.905512</x3>
			<y3>276.931926</y3>
			<x4>197.486741</x4>
			<y4>313.327551</y4>
			<x5>225.61035</x5>
			<y5>223.565256</y5>
			<x6>74.424134</x6>
			<y6>205.289446</y6>
		</polygon>
	</object>
</annotation>
