<annotation>
	<folder></folder>
	<filename>istockphoto-173861869-612x612_jpg.rf.85bea8d3f01f395d289c1d2778b1e868.jpg</filename>
	<path>istockphoto-173861869-612x612_jpg.rf.85bea8d3f01f395d289c1d2778b1e868.jpg</path>
	<source>
		<database>roboflow.com</database>
	</source>
	<size>
		<width>320</width>
		<height>320</height>
		<depth>3</depth>
	</size>
	<segmented>0</segmented>
	<object>
		<name>Tahu</name>
		<pose>Unspecified</pose>
		<truncated>0</truncated>
		<difficult>0</difficult>
		<occluded>0</occluded>
		<bndbox>
			<xmin>86</xmin>
			<xmax>216</xmax>
			<ymin>152</ymin>
			<ymax>295</ymax>
		</bndbox>
	</object>
	<object>
		<name>Tahu</name>
		<pose>Unspecified</pose>
		<truncated>0</truncated>
		<difficult>0</difficult>
		<occluded>0</occluded>
		<bndbox>
			<xmin>36</xmin>
			<xmax>184</xmax>
			<ymin>30</ymin>
			<ymax>155</ymax>
		</bndbox>
	</object>
	<object>
		<name>Tahu</name>
		<pose>Unspecified</pose>
		<truncated>0</truncated>
		<difficult>0</difficult>
		<occluded>0</occluded>
		<bndbox>
			<xmin>173</xmin>
			<xmax>296</xmax>
			<ymin>78</ymin>
			<ymax>263</ymax>
		</bndbox>
		<polygon>
			<x1>235.288721</x1>
			<y1>77.326296</y1>
			<x2>172.305401</x2>
			<y2>118.414567</y2>
			<x3>173.906128</x3>
			<y3>192.358081</y3>
			<x4>223.210066</x4>
			<y4>261.873014</y4>
			<x5>293.086285</x5>
			<y5>236.075972</y5>
			<x6>294.756008</x6>
			<y6>154.036911</y6>
			<x7>235.288721</x7>
			<y7>77.326296</y7>
		</polygon>
	</object>
</annotation>
