<annotation>
	<folder></folder>
	<filename>istockphoto-918019070-612x612_jpg.rf.1de1cb4c5478fe58804f876407ff6199.jpg</filename>
	<path>istockphoto-918019070-612x612_jpg.rf.1de1cb4c5478fe58804f876407ff6199.jpg</path>
	<source>
		<database>roboflow.com</database>
	</source>
	<size>
		<width>320</width>
		<height>320</height>
		<depth>3</depth>
	</size>
	<segmented>0</segmented>
	<object>
		<name>Tahu</name>
		<pose>Unspecified</pose>
		<truncated>0</truncated>
		<difficult>0</difficult>
		<occluded>0</occluded>
		<bndbox>
			<xmin>52</xmin>
			<xmax>277</xmax>
			<ymin>31</ymin>
			<ymax>316</ymax>
		</bndbox>
		<polygon>
			<x1>272.369637</x1>
			<y1>159.6355</y1>
			<x2>275.952793</x2>
			<y2>113.054239</y2>
			<x3>142.181246</x3>
			<y3>29.745466</y3>
			<x4>103.363612</x4>
			<y4>37.80762</y4>
			<x5>51.407698</x5>
			<y5>167.697637</y5>
			<x6>53.199299</x6>
			<y6>215.174694</y6>
			<x7>90.82254</x7>
			<y7>277.296689</y7>
			<x8>149.789435</x8>
			<y8>314.794117</y8>
			<x9>272.369637</x9>
			<y9>159.6355</y9>
		</polygon>
	</object>
	<object>
		<name>Tahu</name>
		<pose>Unspecified</pose>
		<truncated>0</truncated>
		<difficult>0</difficult>
		<occluded>0</occluded>
		<bndbox>
			<xmin>196</xmin>
			<xmax>321</xmax>
			<ymin>117</ymin>
			<ymax>321</ymax>
		</bndbox>
		<polygon>
			<x1>318.353585</x1>
			<y1>319.086716</y1>
			<x2>319.5</x2>
			<y2>132.761699</y2>
			<x3>268.786479</x3>
			<y3>115.741613</y3>
			<x4>195.331554</x4>
			<y4>258.172767</y4>
			<x5>196.101293</x5>
			<y5>319.5</y5>
			<x6>318.353585</x6>
			<y6>319.086716</y6>
		</polygon>
	</object>
</annotation>
