<annotation>
	<folder></folder>
	<filename>nasi-107_jpg.rf.42c2c2c7ee613ac724a4d101ba5a57d0.jpg</filename>
	<path>nasi-107_jpg.rf.42c2c2c7ee613ac724a4d101ba5a57d0.jpg</path>
	<source>
		<database>roboflow.com</database>
	</source>
	<size>
		<width>320</width>
		<height>320</height>
		<depth>3</depth>
	</size>
	<segmented>0</segmented>
	<object>
		<name>Nasi</name>
		<pose>Unspecified</pose>
		<truncated>0</truncated>
		<difficult>0</difficult>
		<occluded>0</occluded>
		<bndbox>
			<xmin>38</xmin>
			<xmax>291</xmax>
			<ymin>1</ymin>
			<ymax>241</ymax>
		</bndbox>
	</object>
</annotation>
